mammos_spindynamics/__init__.py
mammos_spindynamics/db.py
mammos_spindynamics/py.typed
mammos_spindynamics/_ai/__init__.py
mammos_spindynamics/data/db.csv
mammos_spindynamics/data/0001/M.csv
mammos_spindynamics/data/0002/M.csv
mammos_spindynamics/data/0003/M.csv
mammos_spindynamics/data/0004/M.csv
mammos_spindynamics/data/0005/M.csv
mammos_spindynamics/data/0006/M.csv
mammos_spindynamics/data/0007/M.csv
mammos_spindynamics/data/0008/M.csv
mammos_spindynamics/uppasd/__init__.py
mammos_spindynamics/uppasd/_data.py
mammos_spindynamics/uppasd/_inpsd.py
mammos_spindynamics/uppasd/_simulation.py
mammos_spindynamics-0.3.1.dist-info/METADATA
mammos_spindynamics-0.3.1.dist-info/WHEEL
mammos_spindynamics-0.3.1.dist-info/licenses/LICENSE
mammos_spindynamics-0.3.1.dist-info/RECORD
